{
  "project_info": {
    "project_number": "870446661680",
    "project_id": "albumstore-e8440",
    "storage_bucket": "albumstore-e8440.firebasestorage.app"
  },
  "client": [
    {
      "client_info": {
        "mobilesdk_app_id": "1:870446661680:android:141cf392c03db01170adf5",
        "android_client_info": {
          "package_name": "ie.setu.album"
        }
      },
      "oauth_client": [],
      "api_key": [
        {
          "current_key": "AIzaSyBMYy4SGbR5CRlxkCHP7L30KegggQOckpU"
        }
      ],
      "services": {
        "appinvite_service": {
          "other_platform_oauth_client": []
        }
      }
    }
  ],
  "configuration_version": "1"
}